Metadata-Version: 1.0
Name: django-vcs
Version: 0.1
Summary: A pluggable django application to allow browsing of code repositories.
Home-page: http://github.com/alex/django-vcs/
Author: Alex Gaynor, Justin Lilly
Author-email: alex.gaynor@gmail.com
License: UNKNOWN
Platform: UNKNOWN
Classifier: Development Status :: 4 - Beta
Classifier: Intended Audience :: Developers
Classifier: License :: OSI Approved :: BSD License
Classifier: Programming Language :: Python
Classifier: Topic :: Software Development :: Version Control
Classifier: Environment :: Web Environment
Classifier: Framework :: Django
